TideZhongwenWendang/README.md
TideZhongwenWendang/__init__.py
TideZhongwenWendang/__main__.py
TideZhongwenWendang/file.epub
TideZhongwenWendang/index.html
TideZhongwenWendang/css/__init__.py
TideZhongwenWendang/css/annotations.css
TideZhongwenWendang/css/main.css
TideZhongwenWendang/css/normalize.css
TideZhongwenWendang/css/popup.css
TideZhongwenWendang/font/__init__.py
TideZhongwenWendang/font/fontello.eot
TideZhongwenWendang/font/fontello.svg
TideZhongwenWendang/font/fontello.ttf
TideZhongwenWendang/font/fontello.woff
TideZhongwenWendang/img/__init__.py
TideZhongwenWendang/img/annotator-glyph-sprite.png
TideZhongwenWendang/img/annotator-icon-sprite.png
TideZhongwenWendang/img/apple-touch-icon.png
TideZhongwenWendang/img/cancelfullscreen.png
TideZhongwenWendang/img/close.png
TideZhongwenWendang/img/fullscreen.png
TideZhongwenWendang/img/loader.gif
TideZhongwenWendang/img/menu-icon.png
TideZhongwenWendang/img/save.png
TideZhongwenWendang/img/saved.png
TideZhongwenWendang/img/settings-s.png
TideZhongwenWendang/img/settings.png
TideZhongwenWendang/img/star.png
TideZhongwenWendang/js/__init__.py
TideZhongwenWendang/js/epub.js
TideZhongwenWendang/js/epub.min.js
TideZhongwenWendang/js/epub.min.map
TideZhongwenWendang/js/hooks.min.js
TideZhongwenWendang/js/hooks.min.map
TideZhongwenWendang/js/reader.js
TideZhongwenWendang/js/reader.js.map
TideZhongwenWendang/js/reader.min.js
TideZhongwenWendang/js/reader.min.map
TideZhongwenWendang/js/hooks/__init__.py
TideZhongwenWendang/js/hooks/extensions/__init__.py
TideZhongwenWendang/js/hooks/extensions/highlight.js
TideZhongwenWendang/js/libs/__init__.py
TideZhongwenWendang/js/libs/jquery.min.js
TideZhongwenWendang/js/libs/localforage.min.js
TideZhongwenWendang/js/libs/screenfull.js
TideZhongwenWendang/js/libs/screenfull.min.js
TideZhongwenWendang/js/libs/zip.min.js
TideZhongwenWendang/js/plugins/__init__.py
TideZhongwenWendang/js/plugins/hypothesis.js
TideZhongwenWendang/js/plugins/search.js
tide_zhongwen_wendang-2024.3.6.0.dist-info/METADATA
tide_zhongwen_wendang-2024.3.6.0.dist-info/WHEEL
tide_zhongwen_wendang-2024.3.6.0.dist-info/entry_points.txt
tide_zhongwen_wendang-2024.3.6.0.dist-info/top_level.txt
tide_zhongwen_wendang-2024.3.6.0.dist-info/RECORD
